rnt/__init__.py
rnt/rnt.py
rnt/url_functions/__init__.py
rnt/url_functions/url_functions.py
rnt-0.1.7.dist-info/LICENSE
rnt-0.1.7.dist-info/METADATA
rnt-0.1.7.dist-info/WHEEL
rnt-0.1.7.dist-info/top_level.txt
rnt-0.1.7.dist-info/RECORD
