Metadata-Version: 2.1
Name: rnt
Version: 0.1.7
Summary: A simple tool for generating and analyzing Reddit networks.
Home-page: https://github.com/jarohde/rnt
Author: Jacob Rohde
Author-email: jarohde1@gmail.com
Classifier: Programming Language :: Python :: 3
Classifier: License :: OSI Approved :: MIT License
Classifier: Operating System :: OS Independent
Requires-Python: >=3.6
License-File: LICENSE
Requires-Dist: networkx
Requires-Dist: pandas
Requires-Dist: pmaw
Requires-Dist: numpy
